cz_pydata/__init__.py
cz_pydata/cz_pydata.py
cz_pydata/cz_pydata_info.txt
cz_pydata-0.3.0.dist-info/METADATA
cz_pydata-0.3.0.dist-info/WHEEL
cz_pydata-0.3.0.dist-info/entry_points.txt
cz_pydata-0.3.0.dist-info/licenses/LICENSE
cz_pydata-0.3.0.dist-info/RECORD
