Metadata-Version: 2.1
Name: cz-pydata
Version: 0.3.0
Summary: Commitizen plugin for PyData-style commits
Project-URL: Changelog, https://github.com/ghisvail/cz-pydata#changelog
Project-URL: Documentation, https://github.com/ghisvail/cz-pydata#readme
Project-URL: Issues, https://github.com/ghisvail/cz-pydata/issues
Project-URL: Source, https://github.com/ghisvail/cz-pydata
Author-email: Ghislain Vaillant <ghisvail@gmail.com>
License-Expression: MIT
License-File: LICENSE
Keywords: changelog,commitizen,git,pydata
Classifier: Development Status :: 4 - Beta
Classifier: Intended Audience :: Developers
Classifier: License :: OSI Approved :: MIT License
Classifier: Natural Language :: English
Classifier: Operating System :: OS Independent
Classifier: Programming Language :: Python
Classifier: Programming Language :: Python :: 3.8
Classifier: Programming Language :: Python :: 3.9
Classifier: Programming Language :: Python :: 3.10
Classifier: Programming Language :: Python :: 3.11
Classifier: Programming Language :: Python :: 3.12
Requires-Python: >=3.8
Requires-Dist: commitizen>=3.0.0
